{
  "wordcloud_genres": {
    "summary": "Top genres are electronic, hip hop, rap, instrumental, Soundtrack.",
    "top_genres": {
      "electronic": 723,
      "hip hop": 662,
      "rap": 608,
      "instrumental": 481,
      "Soundtrack": 425
    }
  },
  "wordcloud_artists": {
    "summary": "Most listened artists include The Weeknd, League of Legends, Kanye West, Eminem, Radiohead.",
    "top_artists": {
      "The Weeknd": 155,
      "League of Legends": 119,
      "Kanye West": 77,
      "Eminem": 74,
      "Radiohead": 64
    }
  },
  "playcount_distribution": {
    "summary": "Top 5 playlists with the highest total playcounts.",
    "top_playlists": {
      "Street Bars": 7493057555,
      "HARD ROCK": 3482679777,
      "R&B": 3356103488,
      "Post Rock": 2454845931,
      "liked songs": 2032316869
    }
  },
  "artist_genre_playlist_network": {
    "summary": "Network shows strongest links between top artists, genres, and playlists.",
    "top_artists": [
      "The Weeknd",
      "League of Legends",
      "Kanye West",
      "Eminem",
      "Radiohead"
    ],
    "top_genres": [
      "electronic",
      "hip hop",
      "rap",
      "instrumental",
      "Soundtrack"
    ],
    "top_playlists": [
      "Street Bars",
      "Post Rock",
      "R&B",
      "HARD ROCK",
      "liked songs"
    ]
  },
  "polar_playcount_playlist": {
    "min_year": 1952,
    "max_year": 2025,
    "peak_playcount_year": 2011,
    "top_5_tracks": {
      "Yellow": 8738114,
      "A Sky Full of Stars": 8738114,
      "Orphans": 8738114,
      "Fix You": 8738114
    },
    "summary": "Listening history spans from 1952 to 2025, with peak popularity in 2011. Top tracks include Yellow, A Sky Full of Stars, Orphans, Fix You."
  }
}